README.rst
setup.py
jw/__init__.py
jw.ip_service.egg-info/PKG-INFO
jw.ip_service.egg-info/SOURCES.txt
jw.ip_service.egg-info/dependency_links.txt
jw.ip_service.egg-info/entry_points.txt
jw.ip_service.egg-info/namespace_packages.txt
jw.ip_service.egg-info/requires.txt
jw.ip_service.egg-info/top_level.txt
jw/ip_service/__init__.py
jw/ip_service/main.py