Metadata-Version: 1.1
Name: jw.ip-service
Version: 0.1a2
Summary: A tool to set an IP to a network interface for as long as the program runs
Home-page: https://pypi.python.org/pypi/jw.ip-service
Author: Johnny Wezel
Author-email: dev-jay@wezel.name
License: GPL
Download-URL: https://pypi.python.org/packages/source/j/jw.ip-service/jw.ip-service-0.1a2.tar.gz
Keywords: IP,network,interface,utility
Platform: POSIX
Classifier: Development Status :: 5 - Production/Stable
Classifier: Environment :: Console
Classifier: Intended Audience :: System Administrators
Classifier: License :: OSI Approved :: GNU General Public License v3 or later (GPLv3+)
Classifier: Natural Language :: English
Classifier: Operating System :: POSIX
Classifier: Programming Language :: Python :: 2.7
Classifier: Programming Language :: Python :: 3
Classifier: Programming Language :: Python :: 3.4
Classifier: Topic :: System :: Networking
Classifier: Topic :: Utilities
